{
"companyName": "DefaultCompany",
"productName": "Platformer",
"productVersion": "0.1",
"dataUrl": "0d259d79539407395a22951436ad2ab7.unityweb",
"wasmCodeUrl": "192e0f1be105175b842b88ec656c4bfe.unityweb",
"wasmFrameworkUrl": "360b4b283e610d32a599c55b18d592a5.unityweb",
"graphicsAPI": ["WebGL 2.0"],
"webglContextAttributes": {"preserveDrawingBuffer": false},
"splashScreenStyle": "Dark",
"backgroundColor": "#231F20",
"cacheControl": {"default": "must-revalidate"},
"developmentBuild": false,
"multithreading": false,
"unityVersion": "2019.3.7f1"
}